scrapy_time_machine/__init__.py
scrapy_time_machine/storages.py
scrapy_time_machine/timemachine.py
scrapy_time_machine-1.1.1.dist-info/LICENSE
scrapy_time_machine-1.1.1.dist-info/METADATA
scrapy_time_machine-1.1.1.dist-info/WHEEL
scrapy_time_machine-1.1.1.dist-info/top_level.txt
scrapy_time_machine-1.1.1.dist-info/RECORD
