Metadata-Version: 2.1
Name: scrapy-time-machine
Version: 1.1.1
Summary: A downloader middleware that stores the current request chain to be crawled at another time.
Home-page: https://github.com/zytedata/scrapy-time-machine
Author: Luiz Francisco Rodrigues da Silva
Author-email: luizfrdasilva@gmail.com
License: MIT license
Keywords: scrapy cache middleware
Platform: Any
Classifier: Intended Audience :: Developers
Classifier: License :: OSI Approved :: MIT License
Classifier: Natural Language :: English
Classifier: Programming Language :: Python :: 3
Classifier: Programming Language :: Python :: 3.8
Classifier: Programming Language :: Python :: 3.9
Classifier: Programming Language :: Python :: 3.10
Classifier: Programming Language :: Python :: 3.11
License-File: LICENSE
Requires-Dist: Scrapy >=2.0.0
Requires-Dist: boto3
